LICENSE
MANIFEST.in
README.rst
setup.cfg
setup.py
coldcms/VERSION
coldcms/__init__.py
coldcms/__main__.py
coldcms/assets.py
coldcms/urls.py
coldcms/wsgi.py
coldcms.egg-info/PKG-INFO
coldcms.egg-info/SOURCES.txt
coldcms.egg-info/dependency_links.txt
coldcms.egg-info/requires.txt
coldcms.egg-info/top_level.txt
coldcms/blocks/__init__.py
coldcms/blocks/blocks.py
coldcms/blocks/link_page.py
coldcms/blocks/models.py
coldcms/blocks/migrations/0001_initial.py
coldcms/blocks/migrations/0002_auto_20190719_1205.py
coldcms/blocks/migrations/0003_auto_20190725_1326.py
coldcms/blocks/migrations/0004_auto_20200407_1328.py
coldcms/blocks/migrations/__init__.py
coldcms/blocks/templates/blocks/form/color_block_field.html
coldcms/blocks/templatetags/__init__.py
coldcms/blocks/templatetags/navigation_tags.py
coldcms/blog/__init__.py
coldcms/blog/apps.py
coldcms/blog/blocks.py
coldcms/blog/models.py
coldcms/blog/views.py
coldcms/blog/wagtail_hooks.py
coldcms/blog/migrations/0001_initial.py
coldcms/blog/migrations/0002_auto_20190725_1326.py
coldcms/blog/migrations/0003_blogindexpage_keywords.py
coldcms/blog/migrations/0004_blogtaggroupbyblogpage.py
coldcms/blog/migrations/0005_auto_20210805_1730.py
coldcms/blog/migrations/0006_auto_20211123_1120.py
coldcms/blog/migrations/__init__.py
coldcms/blog/templates/blog/blog_index_page.html
coldcms/blog/templates/blog/blog_list_authors_index_page.html
coldcms/blog/templates/blog/blog_list_dates_index_page.html
coldcms/blog/templates/blog/blog_list_tags_index_page.html
coldcms/blog/templates/blog/blog_page.html
coldcms/blog/templates/blog/blog_tag_group_by_blog_page.html
coldcms/blog/templates/blog/index_page.html
coldcms/blog/templates/blog/post.html
coldcms/contact/__init__.py
coldcms/contact/models.py
coldcms/contact/migrations/0001_initial.py
coldcms/contact/migrations/0001_squashed_0004_remove_contactpage_location.py
coldcms/contact/migrations/0002_auto_20190719_0803.py
coldcms/contact/migrations/0002_contactpage_keywords.py
coldcms/contact/migrations/0003_auto_20190725_1326.py
coldcms/contact/migrations/0004_remove_contactpage_location.py
coldcms/contact/migrations/__init__.py
