Metadata-Version: 2.1
Name: coldcms
Version: 0.2.5
Summary: A CMS optimized for low consumption
Home-page: https://coldcms.hashbang.fr
Author: Hashbang
Author-email: contact@hashbang.fr
License: GNU AFFERO GENERAL PUBLIC LICENSE version 3
Project-URL: Documentation, https://coldcms.readthedocs.io/en/latest/
Project-URL: Code, https://gitlab.com/hashbangfr/coldcms
Keywords: cms,django,wagtail,performance,ecology
Platform: UNKNOWN
Provides-Extra: doc
License-File: LICENSE
